NetmikoLibrary/__init__.py
NetmikoLibrary/connection_cache.py
NetmikoLibrary/errors.py
NetmikoLibrary/library.py
NetmikoLibrary/loggers.py
NetmikoLibrary/templates/cli.j2
NetmikoLibrary/templates/cli_parse.j2
NetmikoLibrary/templates/style.css
robotframework_netmiko-1.0.0.dist-info/METADATA
robotframework_netmiko-1.0.0.dist-info/WHEEL
robotframework_netmiko-1.0.0.dist-info/top_level.txt
robotframework_netmiko-1.0.0.dist-info/RECORD
